ScopeFoundry/.gitignore
ScopeFoundry/README.md
ScopeFoundry/__init__.py
ScopeFoundry/__main__.py
ScopeFoundry/cb32_uuid.py
ScopeFoundry/dataset_metadata.py
ScopeFoundry/generate_loaders_py.py
ScopeFoundry/h5_analyze_with_ipynb.py
ScopeFoundry/h5_io.py
ScopeFoundry/hardware.py
ScopeFoundry/helper_funcs.py
ScopeFoundry/ini_io.py
ScopeFoundry/measurement.py
ScopeFoundry/ndarray_interactive.py
ScopeFoundry/operations.py
ScopeFoundry/stored_recipe_control.py
ScopeFoundry/stored_recipe_control.ui
ScopeFoundry/widgets.py
ScopeFoundry/xreload.py
ScopeFoundry/base_app/__init__.py
ScopeFoundry/base_app/base_app.py
ScopeFoundry/base_app/base_microscope_app.py
ScopeFoundry/base_app/base_microscope_app.qss
ScopeFoundry/base_app/base_microscope_app.ui
ScopeFoundry/base_app/base_microscope_app_mdi.py
ScopeFoundry/base_app/base_microscope_app_mdi.ui
ScopeFoundry/base_app/console_widget.py
ScopeFoundry/base_app/logging_handlers.py
ScopeFoundry/base_app/logging_widget.py
ScopeFoundry/base_app/show_io_report_dialog.py
ScopeFoundry/base_app/icons/console_logo.png
ScopeFoundry/base_app/icons/favorite.png
ScopeFoundry/base_app/icons/jupyter_logo.png
ScopeFoundry/base_app/icons/log_logo.png
ScopeFoundry/base_app/icons/scopefoundry_logo2B_1024.png
ScopeFoundry/base_app/icons/scopefoundry_logo2C_1024.png
ScopeFoundry/base_app/icons/scopefoundry_logo2D_1024.png
ScopeFoundry/base_app/icons/scopefoundry_logo2_1024.icns
ScopeFoundry/base_app/icons/scopefoundry_logo2_1024.png
ScopeFoundry/base_app/icons/scopefoundry_logo2_versions.svg
ScopeFoundry/base_app/icons/settings_logo.png
ScopeFoundry/base_app/icons/show_ui_logo.png
ScopeFoundry/controlling/__init__.py
ScopeFoundry/controlling/pid_feedback_control_measure.py
ScopeFoundry/controlling/ranged_optimization.py
ScopeFoundry/controlling/test_app.py
ScopeFoundry/controlling/pid_feedback_control_measure_docs/__place_documentation_here_readme_first.md
ScopeFoundry/controlling/pid_feedback_control_measure_docs/links.json
scopefoundry-2.2.1.dist-info/licenses/LICENSE
scopefoundry-2.2.1.dist-info/METADATA
scopefoundry-2.2.1.dist-info/WHEEL
scopefoundry-2.2.1.dist-info/top_level.txt
scopefoundry-2.2.1.dist-info/RECORD
