Metadata-Version: 2.4
Name: ScopeFoundry
Version: 2.2.1
Summary: a platform for laboratory equipment control and scientific data analysis
Home-page: https://www.scopefoundry.org/
Author: Edward S. Barnard
Author-email: esbarnard@lbl.gov
License: BSD
License-File: LICENSE
Requires-Dist: numpy
Requires-Dist: h5py
Requires-Dist: uuid7
Requires-Dist: qtpy
Requires-Dist: pyqtgraph
Provides-Extra: all
Requires-Dist: PyQt6; extra == "all"
Requires-Dist: qtconsole; extra == "all"
Requires-Dist: pyqtdarktheme; extra == "all"
Requires-Dist: matplotlib; extra == "all"
Dynamic: author
Dynamic: author-email
Dynamic: description
Dynamic: description-content-type
Dynamic: home-page
Dynamic: license
Dynamic: license-file
Dynamic: provides-extra
Dynamic: requires-dist
Dynamic: summary
